common_utils/__init__.py
common_utils/base_service.py
common_utils/connections.py
common_utils/constants.py
common_utils/datetime.py
common_utils/decorators.py
common_utils/errors.py
common_utils/exceptions.py
common_utils/logger.py
common_utils/message.py
common_utils/microservices.py
common_utils/pagination.py
common_utils/response.py
common_utils/swagger.py
common_utils/utils.py
common_utils/validators.py
core/__init__.py
core/asgi.py
core/settings.py
core/urls.py
core/wsgi.py
users/__init__.py
users/admin.py
users/apps.py
users/errors.py
users/models.py
users/serializers.py
users/services.py
users/tests.py
users/urls.py
users/utils.py
users/views.py
users/migrations/0001_initial.py
users/migrations/__init__.py
pm_users-0.1.dist-info/METADATA
pm_users-0.1.dist-info/WHEEL
pm_users-0.1.dist-info/top_level.txt
pm_users-0.1.dist-info/RECORD
